[{"date": "2020-03-08", "locations": [{"name": "Refeitório HSJ", "meals": [{"name": "Almoço", "soup": ["Curgete com alho francês", "Abóbora  com feijão verde"], "meat": ["Folhados de carne com arroz"], "fish": ["Bacalhau em cama de legumes c/arroz"], "diet": ["Bife de frango grelhado com laços"], "vegie": ["Hambúrguer de feijão frade e cenoura com arroz"], "opti": ["Salada morna de laçarotes"]}, {"name": "Jantar", "soup": ["Feijão manteiga couve e cenoura", "Juliana de legumes"], "meat": ["Arroz de tentáculos de pota"], "fish": ["Badejo estufado com puré"], "diet": ["Quiche de frango"], "vegie": [""]}]}]}, {"date": "2020-03-07", "locations": [{"name": "Refeitório HSJ", "meals": [{"name": "Almoço", "soup": ["Creme de abóbora com cenoura ", "Caldo verde"], "meat": ["Arroz de aves no forno"], "fish": ["Perca grelhada com batatas a murro"], "diet": ["Pescada cozida com salada russa"], "vegie": ["Caril de grão com legumes e arroz"], "opti": ["Chili vegetariano com arroz"]}, {"name": "Jantar", "soup": ["Espinafres", "Lombarda"], "meat": ["Peixe espada grelhado c/m. manteiga e bat cozida"], "fish": ["Fêvera grelhada com arroz"], "diet": ["Açorda de marisco"], "vegie": ["JANTAR"]}]}]}, {"date": "2020-03-06", "locations": [{"name": "Refeitório HSJ", "meals": [{"name": "Almoço", "soup": ["Brócolos com nabo e cenoura", "Repolho"], "meat": ["Frango com cogumelos e massa fusilli"], "fish": ["Filetes de sardinha com arroz de tomate"], "diet": ["Coelho estufado simples com puré"], "vegie": ["Salteado de cuscuz com curgete e cenoura"], "opti": ["Empadão de legumes"]}, {"name": "Jantar", "soup": ["Feijão verde laminado", "Espinafres"], "meat": ["Dourada grelhada com batata a murro"], "fish": ["Medalhões de pescada estufºs simples com arroz"], "diet": ["Tripas à Moda do Porto"], "vegie": ["JANTAR"]}]}, {"name": "Cantina UP", "meals": [{"name": "Almoço", "soup": ["Couve-de-bruxelas e curgete "], "meat": ["Bife de peru c/ molho de cogumelos e fusilli salteado "], "fish": ["Salmão assado com batata assada e legumes assados "], "vegie": ["Crepes recheados com grão-de-bico e legumes com fusilli salteado "]}]}, {"name": "Health Bar", "meals": [{"name": "Almoço", "soup": "O HEALTH", "meat": "não fornece", "fish": "a ementa", "vegie": "É uma pena"}]}, {"name": "Yellow Bar & restCIM", "meals": [{"name": "Almoço", "meat": [""], "fish": [""], "vegie": [""]}]}]}, {"date": "2020-03-05", "locations": [{"name": "Refeitório HSJ", "meals": [{"name": "Almoço", "soup": ["Penca com feijão vermelho", "Brócolos "], "meat": ["Shoarma com batata frita arroz"], "fish": ["Empadão de pescada"], "diet": ["Robalo grelhado com arroz"], "vegie": ["Lasanha de legumes"], "opti": ["Quiche de espinafres e arroz"]}, {"name": "Jantar", "soup": ["Abóbora com lombarda", "Alho francês e cenoura "], "meat": ["Paloco à Braga c/arroz e batata pala"], "fish": ["Bifes de frango grelhados com arroz"], "diet": ["Manto de choco grelhado c/ batata cozida"], "vegie": ["JANTAR"]}]}, {"name": "Cantina UP", "meals": [{"name": "Almoço", "soup": ["Penca com feijão vermelho "], "meat": ["Lombo de porco assado com batata assada "], "fish": ["Potas estufadas com arroz de macedónia "], "vegie": ["Caril de seitan e legumes com arroz de macedónia "]}]}, {"name": "Health Bar", "meals": [{"name": "Almoço", "soup": "O HEALTH", "meat": "não fornece", "fish": "a ementa", "vegie": "É uma pena"}]}, {"name": "Yellow Bar & restCIM", "meals": [{"name": "Almoço", "meat": [""], "fish": [""], "vegie": [""]}]}]}, {"date": "2020-03-04", "locations": [{"name": "Refeitório HSJ", "meals": [{"name": "Almoço", "soup": ["Ervilhas", "Nabiças"], "meat": ["Alheira com arroz de chouriço"], "fish": ["Raia dourada com salada russa"], "diet": ["Costeleta grelhada com arroz de legumes"], "vegie": ["Bolinhas de grão com arroz de legumes"], "opti": ["Feijoada à provençal com arroz"]}, {"name": "Jantar", "soup": ["Juliana de legumes", "Penca com nabo"], "meat": ["Pescada à Gomes de Sá"], "fish": ["Carapau grelhado (c/ molho verde) e batata cozida"], "diet": ["Hambúrguer de vaca c/ molho cogumelos e arroz"], "vegie": ["JANTAR"]}]}, {"name": "Cantina UP", "meals": [{"name": "Almoço", "soup": ["Legumes 4 estações (macedónia e nabos) "], "meat": ["Massa à Lavrador (carne de novilho)  "], "fish": ["Badejo de escabeche com puré de 3 legumes  "], "vegie": ["Soja à camponesa com arroz de couves "]}]}, {"name": "Health Bar", "meals": [{"name": "Almoço", "soup": "O HEALTH", "meat": "não fornece", "fish": "a ementa", "vegie": "É uma pena"}]}, {"name": "Yellow Bar & restCIM", "meals": [{"name": "Almoço", "meat": [""], "fish": [""], "vegie": [""]}]}]}, {"date": "2020-03-03", "locations": [{"name": "Refeitório HSJ", "meals": [{"name": "Almoço", "soup": ["Caldo verde", "Grão com espinafres"], "meat": ["Carne de porco à Alentejana (arroz)"], "fish": ["Corvina assada com puré"], "diet": ["Pescada grelhada c/bat cozida, cenoura e couve"], "vegie": ["Canelones de legumes e queijo fresco"], "opti": ["Tomate recheado c/legumes e gratinado, c/arroz"]}, {"name": "Jantar", "soup": ["Alho francês  ", "Feijão verde"], "meat": ["Perca grelhada com batata a murro "], "fish": ["Frango grelhado com arroz de tomate"], "diet": ["Bacalhau à lavrador c/arroz de nabiças "], "vegie": ["JANTAR"]}]}, {"name": "Cantina UP", "meals": [{"name": "Almoço", "soup": ["Creme de abóbora e feijão-verde "], "meat": ["Espetada de porco no forno com arroz de grelos "], "fish": ["Pescada com grelos, broa e batata no forno  "], "vegie": ["Esparguete salteado com tofu, aipo e cenoura "]}]}, {"name": "Health Bar", "meals": [{"name": "Almoço", "soup": "O HEALTH", "meat": "não fornece", "fish": "a ementa", "vegie": "É uma pena"}]}, {"name": "Yellow Bar & restCIM", "meals": [{"name": "Almoço", "meat": [""], "fish": [""], "vegie": [""]}]}]}, {"date": "2020-03-02", "locations": [{"name": "Refeitório HSJ", "meals": [{"name": "Almoço", "soup": ["Grão com espinafres", "Alho francês"], "meat": ["Tiras de peru salteadas em açafrão e esparguete"], "fish": ["Almôndegas de salmão c/m. de tomate e puré"], "diet": ["Carne de vaca estufada simples com arroz"], "vegie": ["Soja tropical com arroz"], "opti": ["Legumes à  Gomes de Sá"]}, {"name": "Jantar", "soup": ["Legumes com cogumelos", "Brócolos e cenoura"], "meat": ["Marmotinha frita com arroz de grelos malandrinho"], "fish": ["Badejo cozido com batata cozida"], "diet": ["Entrecosto assado com batatinha assada e arroz"], "vegie": ["JANTAR"]}]}, {"name": "Cantina UP", "meals": [{"name": "Almoço", "soup": ["Couve-flor, brócolos e feijão branco "], "meat": ["Frango assado com molho à Bairrada com batata frita palha "], "fish": ["Arroz seco de marisco "], "vegie": ["Chili de feijão branco com legumes com arroz de açafrão "]}]}, {"name": "Health Bar", "meals": [{"name": "Almoço", "soup": "O HEALTH", "meat": "não fornece", "fish": "a ementa", "vegie": "É uma pena"}]}, {"name": "Yellow Bar & restCIM", "meals": [{"name": "Almoço", "meat": [""], "fish": [""], "vegie": [""]}]}]}]